F1/__init__.py
F1/__main__.py
F1/fuzzer.py
F1/grammars.py
F1_Fuzzer-0.0.5.dist-info/LICENSE
F1_Fuzzer-0.0.5.dist-info/METADATA
F1_Fuzzer-0.0.5.dist-info/WHEEL
F1_Fuzzer-0.0.5.dist-info/top_level.txt
F1_Fuzzer-0.0.5.dist-info/RECORD
