Metadata-Version: 2.1
Name: F1-Fuzzer
Version: 0.0.5
Summary: A fast grammar fuzzer
Home-page: https://github.com/vrthra/f1
Author: Rahul Gopinath
Author-email: rahul@gopinath.org
License: UNKNOWN
Platform: UNKNOWN
Classifier: Programming Language :: Python :: 3
Classifier: License :: OSI Approved :: MIT License
Classifier: Operating System :: OS Independent
Requires-Python: >=3.6
